ovos_skill_news/LICENSE
ovos_skill_news/MANIFEST.in
ovos_skill_news/News.json
ovos_skill_news/README.md
ovos_skill_news/__init__.py
ovos_skill_news/version.py
ovos_skill_news/locale/ca-es/ca.voc
ovos_skill_news/locale/ca-es/de.voc
ovos_skill_news/locale/ca-es/en-au.voc
ovos_skill_news/locale/ca-es/en-ca.voc
ovos_skill_news/locale/ca-es/en-gb.voc
ovos_skill_news/locale/ca-es/en-us.voc
ovos_skill_news/locale/ca-es/en.voc
ovos_skill_news/locale/ca-es/es.voc
ovos_skill_news/locale/ca-es/euro.voc
ovos_skill_news/locale/ca-es/euronews.voc
ovos_skill_news/locale/ca-es/fi.voc
ovos_skill_news/locale/ca-es/fr.voc
ovos_skill_news/locale/ca-es/fr24.voc
ovos_skill_news/locale/ca-es/global_news.intent
ovos_skill_news/locale/ca-es/it.voc
ovos_skill_news/locale/ca-es/news.error
ovos_skill_news/locale/ca-es/news.intent
ovos_skill_news/locale/ca-es/news.voc
ovos_skill_news/locale/ca-es/nl.voc
ovos_skill_news/locale/ca-es/pt-pt.voc
ovos_skill_news/locale/ca-es/rt.voc
ovos_skill_news/locale/ca-es/ru.voc
ovos_skill_news/locale/ca-es/skill.json
ovos_skill_news/locale/ca-es/sv.voc
ovos_skill_news/locale/ca-es/video.voc
ovos_skill_news/locale/ca-es/world_news.voc
ovos_skill_news/locale/da-dk/ca.voc
ovos_skill_news/locale/da-dk/de.voc
ovos_skill_news/locale/da-dk/en-au.voc
ovos_skill_news/locale/da-dk/en-ca.voc
ovos_skill_news/locale/da-dk/en-gb.voc
ovos_skill_news/locale/da-dk/en-us.voc
ovos_skill_news/locale/da-dk/en.voc
ovos_skill_news/locale/da-dk/es.voc
ovos_skill_news/locale/da-dk/euro.voc
ovos_skill_news/locale/da-dk/euronews.voc
ovos_skill_news/locale/da-dk/fi.voc
ovos_skill_news/locale/da-dk/fr.voc
ovos_skill_news/locale/da-dk/fr24.voc
ovos_skill_news/locale/da-dk/global_news.intent
ovos_skill_news/locale/da-dk/it.voc
ovos_skill_news/locale/da-dk/news.error
ovos_skill_news/locale/da-dk/news.intent
ovos_skill_news/locale/da-dk/news.voc
ovos_skill_news/locale/da-dk/nl.voc
ovos_skill_news/locale/da-dk/pt-pt.voc
ovos_skill_news/locale/da-dk/rt.voc
ovos_skill_news/locale/da-dk/ru.voc
ovos_skill_news/ovos_skill_news.egg-info/PKG-INFO
ovos_skill_news/ovos_skill_news.egg-info/SOURCES.txt
ovos_skill_news/ovos_skill_news.egg-info/dependency_links.txt
ovos_skill_news/ovos_skill_news.egg-info/entry_points.txt
ovos_skill_news/ovos_skill_news.egg-info/requires.txt
ovos_skill_news/ovos_skill_news.egg-info/top_level.txt
ovos_skill_news-0.4.5.dist-info/LICENSE
ovos_skill_news-0.4.5.dist-info/METADATA
ovos_skill_news-0.4.5.dist-info/WHEEL
ovos_skill_news-0.4.5.dist-info/entry_points.txt
ovos_skill_news-0.4.5.dist-info/top_level.txt
ovos_skill_news-0.4.5.dist-info/RECORD
