Metadata-Version: 2.1
Name: ovos-skill-news
Version: 0.4.5
Summary: mycroft/ovos news skill plugin
Home-page: https://github.com/OpenVoiceOS/ovos-skill-news
Author: JarbasAi
Author-email: jarbasai@mailfence.com
License: Apache-2.0
Keywords: ovos skill plugin
License-File: LICENSE
Requires-Dist: beautifulsoup4
Requires-Dist: pytz
Requires-Dist: feedparser~=6.0
Requires-Dist: ovos-bus-client<2.0.0,>=0.0.9
Requires-Dist: ovos-utils[extras]>=0.1.0
Requires-Dist: ovos-workshop<8.0.0,>=0.0.16
